experiments/OLID/__init__.py
experiments/OLID/olid_config.py
experiments/OLID/olid_train.py
offensive_nn/__init__.py
offensive_nn/callbacks.py
offensive_nn/model_args.py
offensive_nn/offensive_nn_model.py
offensive_nn/wrappers.py
offensive_nn/models/__init__.py
offensive_nn/models/layers.py
offensive_nn/models/offensive_capsule_model.py
offensive_nn/models/offensive_cnn1d_model.py
offensive_nn/models/offensive_cnn2d_model.py
offensive_nn/models/offensive_lstm_model.py
offensive_nn/util/__init__.py
offensive_nn/util/evaluation.py
offensive_nn/util/label_converter.py
offensive_nn/util/print_stat.py
offensivenn-0.0.5.dist-info/LICENSE
offensivenn-0.0.5.dist-info/METADATA
offensivenn-0.0.5.dist-info/WHEEL
offensivenn-0.0.5.dist-info/top_level.txt
offensivenn-0.0.5.dist-info/RECORD
