Metadata-Version: 2.1
Name: offensivenn
Version: 0.0.5
Summary: Offensive Language Identification with Neural Networks
Home-page: https://github.com/TharinduDR/https://github.com/TharinduDR/OffensiveNN
Author: Tharindu Ranasinghe
Author-email: rhtdranasinghe@gmail.com
License: UNKNOWN
Platform: UNKNOWN
Classifier: Intended Audience :: Science/Research
Classifier: License :: OSI Approved :: Apache Software License
Classifier: Programming Language :: Python :: 3
Classifier: Topic :: Scientific/Engineering :: Artificial Intelligence
Requires-Python: >=3.6
License-File: LICENSE
Requires-Dist: pandas
Requires-Dist: numpy
Requires-Dist: gensim
Requires-Dist: sklearn
